powerstring.py
powerstring-0.0.1b1.dist-info/METADATA
powerstring-0.0.1b1.dist-info/WHEEL
powerstring-0.0.1b1.dist-info/top_level.txt
powerstring-0.0.1b1.dist-info/RECORD
