Metadata-Version: 2.1
Name: powerstring
Version: 0.0.1b1
Summary: Powerful Strings
Home-page: UNKNOWN
Author: phoenixR
License: MIT
Platform: UNKNOWN
